aiida_orca/__init__.py
aiida_orca/calculations/__init__.py
aiida_orca/calculations/orca_asa.py
aiida_orca/calculations/orca_orca.py
aiida_orca/parsers/__init__.py
aiida_orca/parsers/cclib/LICENSE
aiida_orca/parsers/cclib/__init__.py
aiida_orca/parsers/cclib/ccio.py
aiida_orca/parsers/cclib/data.py
aiida_orca/parsers/cclib/logfileparser.py
aiida_orca/parsers/cclib/orcaparser.py
aiida_orca/parsers/cclib/utils.py
aiida_orca/utils/__init__.py
aiida_orca/utils/input_generator.py
aiida_orca/workchains/__init__.py
aiida_orca/workchains/base.py
aiida_orca-0.7.0.dist-info/entry_points.txt
aiida_orca-0.7.0.dist-info/LICENSE
aiida_orca-0.7.0.dist-info/WHEEL
aiida_orca-0.7.0.dist-info/METADATA
aiida_orca-0.7.0.dist-info/RECORD
