Metadata-Version: 2.1
Name: aiida_orca
Version: 0.7.0
Summary: AiiDA-Orca plugin
Keywords: aiida,orca
Author-email: Pezhman Zarabadi-Poor <pzarabadip@gmail.com>, Daniel Hollas <danekhollas@gmail.com>
Requires-Python: >=3.8
Classifier: Development Status :: 5 - Production/Stable
Classifier: Framework :: AiiDA
Classifier: License :: OSI Approved :: MIT License
Classifier: Operating System :: POSIX :: Linux
Classifier: Operating System :: MacOS :: MacOS X
Classifier: Programming Language :: Python
Classifier: Programming Language :: Python :: 3.8
Classifier: Programming Language :: Python :: 3.9
Classifier: Programming Language :: Python :: 3.10
Classifier: Topic :: Scientific/Engineering
Requires-Dist: aiida_core >= 1.6.0, <3.0.0
Requires-Dist: ase
Requires-Dist: periodictable
Requires-Dist: sphinx ; extra == "docs"
Requires-Dist: sphinxcontrib-contentui ; extra == "docs"
Requires-Dist: sphinxcontrib-details-directive ; extra == "docs"
Requires-Dist: sphinx-rtd-theme ; extra == "docs"
Requires-Dist: mypy>=0.930,<1.0.0 ; extra == "pre-commit"
Requires-Dist: pre-commit~=2.2 ; extra == "pre-commit"
Requires-Dist: yapf==0.28.0 ; extra == "pre-commit"
Requires-Dist: pylint==2.11.1 ; extra == "pre-commit"
Requires-Dist: pgtest==1.2.0 ; extra == "test"
Requires-Dist: pytest~=6.0 ; extra == "test"
Requires-Dist: pytest-cov~=4.0 ; extra == "test"
Requires-Dist: pytest-regressions~=2.3 ; extra == "test"
Project-URL: Home, https://github.com/pzarabadip/aiida-orca
Provides-Extra: docs
Provides-Extra: pre-commit
Provides-Extra: test
